{"countries":[{"name":"ALBANIA","slug":"albania","count":4},{"name":"AUSTRIA","slug":"austria","count":6},{"name":"BELARUS","slug":"belarus","count":1},{"name":"BELGIUM","slug":"belgium","count":8},{"name":"BOSNIA HERZEGOVINA","slug":"bosnia_herzegovina","count":1},{"name":"BULGARIA","slug":"bulgaria","count":2},{"name":"CROATIA","slug":"croatia","count":6},{"name":"CZECH REPUBLIC","slug":"czech_republic","count":5},{"name":"DENMARK","slug":"denmark","count":3},{"name":"FINLAND","slug":"finland","count":3},{"name":"FRANCE","slug":"france","count":11},{"name":"GERMANY","slug":"germany","count":16},{"name":"GREECE","slug":"greece","count":3},{"name":"HUNGARY","slug":"hungary","count":4},{"name":"ICELAND","slug":"iceland","count":4},{"name":"IRELAND","slug":"ireland","count":6},{"name":"ITALY","slug":"italy","count":14},{"name":"KOSOVO","slug":"kosovo","count":2},{"name":"LUXEMBOURG","slug":"luxembourg","count":1},{"name":"MOLDOVA","slug":"moldova","count":2},{"name":"NETHERLANDS","slug":"netherlands","count":2},{"name":"NORWAY","slug":"norway","count":4},{"name":"POLAND","slug":"poland","count":2},{"name":"PORTUGAL","slug":"portugal","count":2},{"name":"ROMANIA","slug":"romania","count":2},{"name":"SLOVAKIA","slug":"slovakia","count":5},{"name":"SLOVENIA","slug":"slovenia","count":3},{"name":"SPAIN","slug":"spain","count":12},{"name":"SWEDEN","slug":"sweden","count":7},{"name":"SWITZERLAND","slug":"switzerland","count":4},{"name":"TURKEY","slug":"turkey","count":1},{"name":"UKRAINE","slug":"ukraine","count":7},{"name":"UNITED KINGDOM","slug":"united_kingdom","count":11}],"resources":[]}