[{"id":"OSM-dj-facebook","type":"facebook","account":"OpenStreetMapDjibouti","locationSet":{"include":["dj"]},"languageCodes":[{"code":"en","name":"English"}],"strings":{"community":"OpenStreetMap Djibouti"},"resolved":{"name":"OpenStreetMap Djibouti on Facebook","url":"https://facebook.com/OpenStreetMapDjibouti","description":"Join our community on Facebook","nameHTML":"<a target=\"_blank\" href=\"https://facebook.com/OpenStreetMapDjibouti\">OpenStreetMap Djibouti on Facebook</a>","urlHTML":"<a target=\"_blank\" href=\"https://facebook.com/OpenStreetMapDjibouti\">https://facebook.com/OpenStreetMapDjibouti</a>","descriptionHTML":"Join our community on Facebook"}},{"id":"OSM-dj-twitter","type":"twitter","account":"djiboutiosm","locationSet":{"include":["dj"]},"languageCodes":[{"code":"en","name":"English"}],"strings":{"community":"OpenStreetMap Djibouti"},"resolved":{"name":"OpenStreetMap Djibouti on Twitter","url":"https://twitter.com/djiboutiosm","description":"Follow us on Twitter","nameHTML":"<a target=\"_blank\" href=\"https://twitter.com/djiboutiosm\">OpenStreetMap Djibouti on Twitter</a>","urlHTML":"<a target=\"_blank\" href=\"https://twitter.com/djiboutiosm\">https://twitter.com/djiboutiosm</a>","descriptionHTML":"Follow us on Twitter"}}]